{
	"name": "Kohl's Admin",
	"image": "mcr.microsoft.com/devcontainers/base:ubuntu",
	"features": {
		"ghcr.io/ryanlua/features/rojo:0.2.0": {
			"version": "latest",
			"toolchainManager": "rokit"
		},
		"ghcr.io/devcontainers/features/node:1": {}
	},
	"customizations": {
		"vscode": {
			"extensions": [
				"evaera.vscode-rojo",
				"Kampfkarren.selene-vscode",
				"JohnnyMorganz.stylua",
				"JohnnyMorganz.luau-lsp"
			]
		}
	},
	"forwardPorts": [
		3000,
		34872
	],
	"portsAttributes": {
		"3000": {
			"label": "Moonwave",
			"onAutoForward": "openPreview"
		},
		"34872": {
			"label": "Rojo"
		}
	},
	"postCreateCommand": "git config submodule.recurse true && git config pull.rebase true && rokit install --no-trust-check && npm i -g moonwave",
	"remoteUser": "root"
}